setup.py
impaf_flashmsg.egg-info/PKG-INFO
impaf_flashmsg.egg-info/SOURCES.txt
impaf_flashmsg.egg-info/dependency_links.txt
impaf_flashmsg.egg-info/namespace_packages.txt
impaf_flashmsg.egg-info/not-zip-safe
impaf_flashmsg.egg-info/requires.txt
impaf_flashmsg.egg-info/top_level.txt
implugin/__init__.py
implugin/flashmsg/__init__.py
implugin/flashmsg/controller.py
implugin/flashmsg/models.py
implugin/flashmsg/requestable.py
implugin/flashmsg/testing.py
implugin/flashmsg/widget.py
implugin/flashmsg/tests/__init__.py
implugin/flashmsg/tests/test_controllers.py
implugin/flashmsg/tests/test_models.py
implugin/flashmsg/tests/test_requestable.py
implugin/flashmsg/tests/test_widget.py